salascorp_descriptive/__init__.py
salascorp_descriptive/kolmogorov_widget.py
salascorp_descriptive-0.3.0.dist-info/LICENSE
salascorp_descriptive-0.3.0.dist-info/METADATA
salascorp_descriptive-0.3.0.dist-info/WHEEL
salascorp_descriptive-0.3.0.dist-info/top_level.txt
salascorp_descriptive-0.3.0.dist-info/RECORD
